airflow_provider_coiled-0.0.24.dist-info/licenses/LICENSE
coiled_provider/__init__.py
coiled_provider/get_provider_info.py
coiled_provider/operators/__init__.py
coiled_provider/operators/cluster.py
airflow_provider_coiled-0.0.24.dist-info/METADATA
airflow_provider_coiled-0.0.24.dist-info/WHEEL
airflow_provider_coiled-0.0.24.dist-info/entry_points.txt
airflow_provider_coiled-0.0.24.dist-info/top_level.txt
airflow_provider_coiled-0.0.24.dist-info/RECORD
