Metadata-Version: 2.4
Name: airflow-provider-coiled
Version: 0.0.24
Summary: A sample Apache Airflow provider package built by Astronomer.
Author-email: Pete DeJoy <pete@astronomer.io>, Josh Fell <josh.d.fell@astronomer.io>, Astronomer <humans@astronomer.io>
License: Apache License 2.0
Project-URL: Homepage, https://astronomer.io
Project-URL: Source, https://github.com/astronomer/airflow-provider-sample/
Classifier: Framework :: Apache Airflow
Classifier: Framework :: Apache Airflow :: Provider
Requires-Python: ~=3.8
License-File: LICENSE
Requires-Dist: apache-airflow>=2.4
Dynamic: license-file
